toon_ld-0.2.1.dist-info/METADATA
toon_ld-0.2.1.dist-info/WHEEL
toon_ld/__init__.pyi
toon_ld/toon_ld.abi3.so
toon_ld-0.2.1.dist-info/RECORD
