Metadata-Version: 2.4
Name: toon-ld
Version: 0.2.1
Classifier: Development Status :: 4 - Beta
Classifier: Intended Audience :: Developers
Classifier: License :: OSI Approved :: MIT License
Classifier: Operating System :: OS Independent
Classifier: Programming Language :: Python :: 3
Classifier: Programming Language :: Python :: 3.8
Classifier: Programming Language :: Python :: 3.9
Classifier: Programming Language :: Python :: 3.10
Classifier: Programming Language :: Python :: 3.11
Classifier: Programming Language :: Python :: 3.12
Classifier: Programming Language :: Rust
Classifier: Topic :: Software Development :: Libraries :: Python Modules
Classifier: Topic :: Text Processing :: Markup
Requires-Dist: pytest>=7.0 ; extra == 'dev'
Requires-Dist: pytest-benchmark>=4.0 ; extra == 'dev'
Provides-Extra: dev
Summary: High-performance serializer/parser for TOON-LD (Token-Oriented Object Notation for Linked Data)
Keywords: toon,json-ld,rdf,linked-data,serialization
Author: TOON-LD Contributors
License: MIT
Requires-Python: >=3.8
Project-URL: Homepage, https://github.com/toon-ld/toon-ld
Project-URL: Repository, https://github.com/toon-ld/toon-ld
Project-URL: Documentation, https://github.com/toon-ld/toon-ld#readme
